{
  "_descripcion": "Alertas mock para demostración. Cada alerta tiene tipo, zona, nivel, acción y producto BP sugerido.",
  "alertas": [
    {
      "id": 1,
      "tipo": "estres_hidrico",
      "titulo": "Reserva de agua crítica — 2 semanas consecutivas bajo umbral",
      "zona": "Pergamino",
      "provincia": "Buenos Aires",
      "depto_id": "06609",
      "nivel": "alto",
      "score": 88,
      "accion": "Contactar productores de la zona. Ofrecer capital de trabajo y refinanciación preventiva.",
      "producto_bp": "Capital de Trabajo PIV + Refinanciación",
      "fecha": "2026-03-24",
      "estado": "nueva"
    },
    {
      "id": 2,
      "tipo": "estres_hidrico",
      "titulo": "NDVI cayó 18% vs. promedio histórico en últimas 3 semanas",
      "zona": "9 de Julio",
      "provincia": "Buenos Aires",
      "depto_id": "06560",
      "nivel": "alto",
      "score": 84,
      "accion": "Zona con maíz en etapa crítica. Evaluar impacto en rendimiento y ofrecer cobertura.",
      "producto_bp": "Seguro agropecuario + Cap. Trabajo",
      "fecha": "2026-03-23",
      "estado": "nueva"
    },
    {
      "id": 3,
      "tipo": "emergencia",
      "titulo": "Emergencia agropecuaria declarada por sequía prolongada",
      "zona": "Carlos Tejedor",
      "provincia": "Buenos Aires",
      "depto_id": "06189",
      "nivel": "critico",
      "score": 70,
      "accion": "Activar protocolo de emergencia. Ofrecer refinanciación con tasa bonificada.",
      "producto_bp": "Refinanciación emergencia — tasa bonificada BADLAR 80% RO",
      "fecha": "2026-03-22",
      "estado": "nueva"
    },
    {
      "id": 4,
      "tipo": "cambio_productivo",
      "titulo": "Expansión de maíz: +22% superficie sembrada vs. campaña anterior",
      "zona": "Marcos Juárez",
      "provincia": "Córdoba",
      "depto_id": "14014",
      "nivel": "medio",
      "score": 86,
      "accion": "Zona en reconversión productiva. Oportunidad de financiar campaña e insumos.",
      "producto_bp": "Préstamo Siembra + Procampo Digital",
      "fecha": "2026-03-21",
      "estado": "vista"
    },
    {
      "id": 5,
      "tipo": "oportunidad_inversion",
      "titulo": "Mejora hídrica sostenida + perfil intensivo creciente",
      "zona": "General López",
      "provincia": "Santa Fe",
      "depto_id": "82063",
      "nivel": "medio",
      "score": 83,
      "accion": "Zona con condiciones favorables para inversión. Ofrecer líneas de maquinaria y riego.",
      "producto_bp": "Préstamo Inversión (Ganados y Carnes) + Procampo Digital USD",
      "fecha": "2026-03-20",
      "estado": "nueva"
    },
    {
      "id": 6,
      "tipo": "zona_subasegurada",
      "titulo": "Alto riesgo climático con baja penetración de seguros",
      "zona": "General Villegas",
      "provincia": "Buenos Aires",
      "depto_id": "06322",
      "nivel": "medio",
      "score": 66,
      "accion": "Zona vulnerable sin cobertura. Derivar a área de seguros antes de ventana crítica.",
      "producto_bp": "Seguro agropecuario (derivar a Provincia Seguros)",
      "fecha": "2026-03-19",
      "estado": "nueva"
    },
    {
      "id": 7,
      "tipo": "estres_hidrico",
      "titulo": "Reserva de agua descendente — tendencia negativa 4 semanas",
      "zona": "Rojas",
      "provincia": "Buenos Aires",
      "depto_id": "06700",
      "nivel": "alto",
      "score": 80,
      "accion": "Trigo en zona afectada. Evaluar necesidad de capital de trabajo para cubrir bache.",
      "producto_bp": "Capital de Trabajo PAIV",
      "fecha": "2026-03-18",
      "estado": "vista"
    },
    {
      "id": 8,
      "tipo": "cambio_productivo",
      "titulo": "Cambio de cultivo principal: girasol → soja en últimas 2 campañas",
      "zona": "Pehuajó",
      "provincia": "Buenos Aires",
      "depto_id": "06623",
      "nivel": "bajo",
      "score": 64,
      "accion": "Monitorear evolución. Productores pueden necesitar nuevos insumos.",
      "producto_bp": "Procampo Digital (insumos)",
      "fecha": "2026-03-17",
      "estado": "vista"
    },
    {
      "id": 9,
      "tipo": "oportunidad_inversion",
      "titulo": "Zona lechera con indicadores de expansión de tambo",
      "zona": "Caseros",
      "provincia": "Santa Fe",
      "depto_id": "82028",
      "nivel": "medio",
      "score": 77,
      "accion": "Oportunidad para financiar inversión en lechería: instalaciones y retención de vientres.",
      "producto_bp": "Préstamos Lechería (inversión) — hasta $5M",
      "fecha": "2026-03-16",
      "estado": "nueva"
    },
    {
      "id": 10,
      "tipo": "estres_hidrico",
      "titulo": "Precipitación acumulada 40% debajo de la media histórica",
      "zona": "Junín",
      "provincia": "Buenos Aires",
      "depto_id": "06413",
      "nivel": "alto",
      "score": 82,
      "accion": "Soja en etapa de llenado de grano afectada. Anticipar necesidad de refinanciación.",
      "producto_bp": "Refinanciación + Capital de Trabajo",
      "fecha": "2026-03-15",
      "estado": "nueva"
    },
    {
      "id": 11,
      "tipo": "zona_subasegurada",
      "titulo": "Zona arrocera sin cobertura contra exceso hídrico",
      "zona": "Villaguay",
      "provincia": "Entre Ríos",
      "depto_id": "30113",
      "nivel": "medio",
      "score": 63,
      "accion": "Arroz vulnerable a exceso hídrico. Ofrecer seguro paramétrico o tradicional.",
      "producto_bp": "Seguro agropecuario (exceso hídrico)",
      "fecha": "2026-03-14",
      "estado": "nueva"
    },
    {
      "id": 12,
      "tipo": "emergencia",
      "titulo": "Solicitud de prórroga activa — emergencia vigente desde enero",
      "zona": "Lincoln",
      "provincia": "Buenos Aires",
      "depto_id": "06455",
      "nivel": "alto",
      "score": 68,
      "accion": "Verificar estado de prórrogas. Ofrecer reprogramación de deuda.",
      "producto_bp": "Reprogramación/refinanciación de deuda agro",
      "fecha": "2026-03-13",
      "estado": "asignada"
    },
    {
      "id": 13,
      "tipo": "oportunidad_inversion",
      "titulo": "Zona ganadera con mejora de precios y pasturas en buen estado",
      "zona": "Guaminí",
      "provincia": "Buenos Aires",
      "depto_id": "06371",
      "nivel": "bajo",
      "score": 52,
      "accion": "Oportunidad moderada. Monitorear para siguiente trimestre.",
      "producto_bp": "Préstamos Ganados y Carnes (retención de vientres)",
      "fecha": "2026-03-12",
      "estado": "vista"
    },
    {
      "id": 14,
      "tipo": "cambio_productivo",
      "titulo": "Incremento de superficie de cebada: +15% vs. campaña anterior",
      "zona": "Unión",
      "provincia": "Córdoba",
      "depto_id": "14126",
      "nivel": "bajo",
      "score": 71,
      "accion": "Diversificación productiva en curso. Posible demanda de insumos específicos.",
      "producto_bp": "Procampo Digital + Préstamo Siembra",
      "fecha": "2026-03-11",
      "estado": "nueva"
    },
    {
      "id": 15,
      "tipo": "estres_hidrico",
      "titulo": "Déficit hídrico moderado en zona mixta",
      "zona": "Río Cuarto",
      "provincia": "Córdoba",
      "depto_id": "14098",
      "nivel": "medio",
      "score": 75,
      "accion": "Monitorear próximas semanas. Si persiste, activar oferta defensiva.",
      "producto_bp": "Capital de Trabajo (preventivo)",
      "fecha": "2026-03-10",
      "estado": "nueva"
    }
  ]
}
